nosespec.py
setup.py
nosespec.egg-info/PKG-INFO
nosespec.egg-info/SOURCES.txt
nosespec.egg-info/dependency_links.txt
nosespec.egg-info/entry_points.txt
nosespec.egg-info/top_level.txt