Metadata-Version: 1.0
Name: nosespec
Version: 0.1
Summary: Spec plugin for nosetests
Home-page: UNKNOWN
Author: Anatoly Kudinov
Author-email: zz@rialabs.org
License: UNKNOWN
Platform: UNKNOWN
